examples/__init__.py
examples/fugue_spark.py
examples/native_spark.py
node2vec/__init__.py
node2vec/constants.py
node2vec/embedding.py
node2vec/fugue.py
node2vec/indexer.py
node2vec/randomwalk.py
node2vec/spark.py
tests/__init__.py
tests/test_constants.py
tests/test_embedding.py
tests/test_fugue.py
tests/test_indexer.py
tests/test_randomwalk.py
node2vec_fugue-0.3.4.dist-info/LICENSE
node2vec_fugue-0.3.4.dist-info/METADATA
node2vec_fugue-0.3.4.dist-info/WHEEL
node2vec_fugue-0.3.4.dist-info/top_level.txt
node2vec_fugue-0.3.4.dist-info/RECORD
