Metadata-Version: 2.1
Name: node2vec-fugue
Version: 0.3.4
Summary: Highly Scalable Distributed Node2Vec Algorithm Library
Home-page: http://github.com/fugue-project/node2vec
Author: Jintao Zhang
Author-email: jtzhang@gmail.com
License: Apache-2.0
Keywords: graph embedding
Platform: UNKNOWN
Classifier: Development Status :: 3 - Alpha
Classifier: Intended Audience :: Developers
Classifier: Topic :: Software Development :: Libraries :: Python Modules
Classifier: License :: OSI Approved :: Apache Software License
Classifier: Natural Language :: English
Classifier: Programming Language :: Python :: 3.7
Classifier: Programming Language :: Python :: 3.6
Classifier: Programming Language :: Python :: 3 :: Only
Requires-Dist: PyYAML
Requires-Dist: future
Requires-Dist: pathlib2
Requires-Dist: six
Requires-Dist: joblib
Requires-Dist: pypandoc
